{
 "pytest_workflow":{
  "__set__":true,
  "elements":[
   "pytest-workflow-1.2.0-py_0",
   "pytest-workflow-1.2.1-py_0",
   "pytest-workflow-1.2.2-py_0",
   "pytest-workflow-1.3.0-py_0",
   "pytest-workflow-1.5.0-pyhd8ed1ab_0"
  ]
 },
 "pytest_workflow.content_tests":{
  "__set__":true,
  "elements":[
   "pytest-workflow-1.2.0-py_0",
   "pytest-workflow-1.2.1-py_0",
   "pytest-workflow-1.2.2-py_0",
   "pytest-workflow-1.3.0-py_0",
   "pytest-workflow-1.5.0-pyhd8ed1ab_0"
  ]
 },
 "pytest_workflow.content_tests.ContentTestCollector":{
  "__set__":true,
  "elements":[
   "pytest-workflow-1.2.0-py_0",
   "pytest-workflow-1.2.1-py_0",
   "pytest-workflow-1.2.2-py_0",
   "pytest-workflow-1.3.0-py_0",
   "pytest-workflow-1.5.0-pyhd8ed1ab_0"
  ]
 },
 "pytest_workflow.content_tests.ContentTestCollector.__init__":{
  "__set__":true,
  "elements":[
   "pytest-workflow-1.2.0-py_0",
   "pytest-workflow-1.2.1-py_0",
   "pytest-workflow-1.2.2-py_0",
   "pytest-workflow-1.3.0-py_0",
   "pytest-workflow-1.5.0-pyhd8ed1ab_0"
  ]
 },
 "pytest_workflow.content_tests.ContentTestCollector.collect":{
  "__set__":true,
  "elements":[
   "pytest-workflow-1.2.0-py_0",
   "pytest-workflow-1.2.1-py_0",
   "pytest-workflow-1.2.2-py_0",
   "pytest-workflow-1.3.0-py_0",
   "pytest-workflow-1.5.0-pyhd8ed1ab_0"
  ]
 },
 "pytest_workflow.content_tests.ContentTestCollector.find_strings":{
  "__set__":true,
  "elements":[
   "pytest-workflow-1.2.0-py_0",
   "pytest-workflow-1.2.1-py_0",
   "pytest-workflow-1.2.2-py_0",
   "pytest-workflow-1.3.0-py_0",
   "pytest-workflow-1.5.0-pyhd8ed1ab_0"
  ]
 },
 "pytest_workflow.content_tests.ContentTestItem":{
  "__set__":true,
  "elements":[
   "pytest-workflow-1.2.0-py_0",
   "pytest-workflow-1.2.1-py_0",
   "pytest-workflow-1.2.2-py_0",
   "pytest-workflow-1.3.0-py_0",
   "pytest-workflow-1.5.0-pyhd8ed1ab_0"
  ]
 },
 "pytest_workflow.content_tests.ContentTestItem.__init__":{
  "__set__":true,
  "elements":[
   "pytest-workflow-1.2.0-py_0",
   "pytest-workflow-1.2.1-py_0",
   "pytest-workflow-1.2.2-py_0",
   "pytest-workflow-1.3.0-py_0",
   "pytest-workflow-1.5.0-pyhd8ed1ab_0"
  ]
 },
 "pytest_workflow.content_tests.ContentTestItem.repr_failure":{
  "__set__":true,
  "elements":[
   "pytest-workflow-1.2.0-py_0",
   "pytest-workflow-1.2.1-py_0",
   "pytest-workflow-1.2.2-py_0",
   "pytest-workflow-1.3.0-py_0",
   "pytest-workflow-1.5.0-pyhd8ed1ab_0"
  ]
 },
 "pytest_workflow.content_tests.ContentTestItem.runtest":{
  "__set__":true,
  "elements":[
   "pytest-workflow-1.2.0-py_0",
   "pytest-workflow-1.2.1-py_0",
   "pytest-workflow-1.2.2-py_0",
   "pytest-workflow-1.3.0-py_0",
   "pytest-workflow-1.5.0-pyhd8ed1ab_0"
  ]
 },
 "pytest_workflow.content_tests.check_content":{
  "__set__":true,
  "elements":[
   "pytest-workflow-1.2.0-py_0",
   "pytest-workflow-1.2.1-py_0",
   "pytest-workflow-1.2.2-py_0",
   "pytest-workflow-1.3.0-py_0",
   "pytest-workflow-1.5.0-pyhd8ed1ab_0"
  ]
 },
 "pytest_workflow.content_tests.check_regex_content":{
  "__set__":true,
  "elements":[
   "pytest-workflow-1.5.0-pyhd8ed1ab_0"
  ]
 },
 "pytest_workflow.content_tests.file_to_string_generator":{
  "__set__":true,
  "elements":[
   "pytest-workflow-1.2.0-py_0",
   "pytest-workflow-1.2.1-py_0",
   "pytest-workflow-1.2.2-py_0"
  ]
 },
 "pytest_workflow.file_tests":{
  "__set__":true,
  "elements":[
   "pytest-workflow-1.2.0-py_0",
   "pytest-workflow-1.2.1-py_0",
   "pytest-workflow-1.2.2-py_0",
   "pytest-workflow-1.3.0-py_0",
   "pytest-workflow-1.5.0-pyhd8ed1ab_0"
  ]
 },
 "pytest_workflow.file_tests.FileExists":{
  "__set__":true,
  "elements":[
   "pytest-workflow-1.2.0-py_0",
   "pytest-workflow-1.2.1-py_0",
   "pytest-workflow-1.2.2-py_0",
   "pytest-workflow-1.3.0-py_0",
   "pytest-workflow-1.5.0-pyhd8ed1ab_0"
  ]
 },
 "pytest_workflow.file_tests.FileExists.__init__":{
  "__set__":true,
  "elements":[
   "pytest-workflow-1.2.0-py_0",
   "pytest-workflow-1.2.1-py_0",
   "pytest-workflow-1.2.2-py_0",
   "pytest-workflow-1.3.0-py_0",
   "pytest-workflow-1.5.0-pyhd8ed1ab_0"
  ]
 },
 "pytest_workflow.file_tests.FileExists.repr_failure":{
  "__set__":true,
  "elements":[
   "pytest-workflow-1.2.0-py_0",
   "pytest-workflow-1.2.1-py_0",
   "pytest-workflow-1.2.2-py_0",
   "pytest-workflow-1.3.0-py_0",
   "pytest-workflow-1.5.0-pyhd8ed1ab_0"
  ]
 },
 "pytest_workflow.file_tests.FileExists.runtest":{
  "__set__":true,
  "elements":[
   "pytest-workflow-1.2.0-py_0",
   "pytest-workflow-1.2.1-py_0",
   "pytest-workflow-1.2.2-py_0",
   "pytest-workflow-1.3.0-py_0",
   "pytest-workflow-1.5.0-pyhd8ed1ab_0"
  ]
 },
 "pytest_workflow.file_tests.FileMd5":{
  "__set__":true,
  "elements":[
   "pytest-workflow-1.2.0-py_0",
   "pytest-workflow-1.2.1-py_0",
   "pytest-workflow-1.2.2-py_0",
   "pytest-workflow-1.3.0-py_0",
   "pytest-workflow-1.5.0-pyhd8ed1ab_0"
  ]
 },
 "pytest_workflow.file_tests.FileMd5.__init__":{
  "__set__":true,
  "elements":[
   "pytest-workflow-1.2.0-py_0",
   "pytest-workflow-1.2.1-py_0",
   "pytest-workflow-1.2.2-py_0",
   "pytest-workflow-1.3.0-py_0",
   "pytest-workflow-1.5.0-pyhd8ed1ab_0"
  ]
 },
 "pytest_workflow.file_tests.FileMd5.repr_failure":{
  "__set__":true,
  "elements":[
   "pytest-workflow-1.2.0-py_0",
   "pytest-workflow-1.2.1-py_0",
   "pytest-workflow-1.2.2-py_0",
   "pytest-workflow-1.3.0-py_0",
   "pytest-workflow-1.5.0-pyhd8ed1ab_0"
  ]
 },
 "pytest_workflow.file_tests.FileMd5.runtest":{
  "__set__":true,
  "elements":[
   "pytest-workflow-1.2.0-py_0",
   "pytest-workflow-1.2.1-py_0",
   "pytest-workflow-1.2.2-py_0",
   "pytest-workflow-1.3.0-py_0",
   "pytest-workflow-1.5.0-pyhd8ed1ab_0"
  ]
 },
 "pytest_workflow.file_tests.FileTestCollector":{
  "__set__":true,
  "elements":[
   "pytest-workflow-1.2.0-py_0",
   "pytest-workflow-1.2.1-py_0",
   "pytest-workflow-1.2.2-py_0",
   "pytest-workflow-1.3.0-py_0",
   "pytest-workflow-1.5.0-pyhd8ed1ab_0"
  ]
 },
 "pytest_workflow.file_tests.FileTestCollector.__init__":{
  "__set__":true,
  "elements":[
   "pytest-workflow-1.2.0-py_0",
   "pytest-workflow-1.2.1-py_0",
   "pytest-workflow-1.2.2-py_0",
   "pytest-workflow-1.3.0-py_0",
   "pytest-workflow-1.5.0-pyhd8ed1ab_0"
  ]
 },
 "pytest_workflow.file_tests.FileTestCollector.collect":{
  "__set__":true,
  "elements":[
   "pytest-workflow-1.2.0-py_0",
   "pytest-workflow-1.2.1-py_0",
   "pytest-workflow-1.2.2-py_0",
   "pytest-workflow-1.3.0-py_0",
   "pytest-workflow-1.5.0-pyhd8ed1ab_0"
  ]
 },
 "pytest_workflow.file_tests.file_md5sum":{
  "__set__":true,
  "elements":[
   "pytest-workflow-1.2.0-py_0",
   "pytest-workflow-1.2.1-py_0",
   "pytest-workflow-1.2.2-py_0",
   "pytest-workflow-1.3.0-py_0"
  ]
 },
 "pytest_workflow.plugin":{
  "__set__":true,
  "elements":[
   "pytest-workflow-1.2.0-py_0",
   "pytest-workflow-1.2.1-py_0",
   "pytest-workflow-1.2.2-py_0",
   "pytest-workflow-1.3.0-py_0",
   "pytest-workflow-1.5.0-pyhd8ed1ab_0"
  ]
 },
 "pytest_workflow.plugin.ExitCodeTest":{
  "__set__":true,
  "elements":[
   "pytest-workflow-1.2.0-py_0",
   "pytest-workflow-1.2.1-py_0",
   "pytest-workflow-1.2.2-py_0",
   "pytest-workflow-1.3.0-py_0",
   "pytest-workflow-1.5.0-pyhd8ed1ab_0"
  ]
 },
 "pytest_workflow.plugin.ExitCodeTest.__init__":{
  "__set__":true,
  "elements":[
   "pytest-workflow-1.2.0-py_0",
   "pytest-workflow-1.2.1-py_0",
   "pytest-workflow-1.2.2-py_0",
   "pytest-workflow-1.3.0-py_0",
   "pytest-workflow-1.5.0-pyhd8ed1ab_0"
  ]
 },
 "pytest_workflow.plugin.ExitCodeTest.repr_failure":{
  "__set__":true,
  "elements":[
   "pytest-workflow-1.2.0-py_0",
   "pytest-workflow-1.2.1-py_0",
   "pytest-workflow-1.2.2-py_0",
   "pytest-workflow-1.3.0-py_0",
   "pytest-workflow-1.5.0-pyhd8ed1ab_0"
  ]
 },
 "pytest_workflow.plugin.ExitCodeTest.runtest":{
  "__set__":true,
  "elements":[
   "pytest-workflow-1.2.0-py_0",
   "pytest-workflow-1.2.1-py_0",
   "pytest-workflow-1.2.2-py_0",
   "pytest-workflow-1.3.0-py_0",
   "pytest-workflow-1.5.0-pyhd8ed1ab_0"
  ]
 },
 "pytest_workflow.plugin.WorkflowTestsCollector":{
  "__set__":true,
  "elements":[
   "pytest-workflow-1.2.0-py_0",
   "pytest-workflow-1.2.1-py_0",
   "pytest-workflow-1.2.2-py_0",
   "pytest-workflow-1.3.0-py_0",
   "pytest-workflow-1.5.0-pyhd8ed1ab_0"
  ]
 },
 "pytest_workflow.plugin.WorkflowTestsCollector.__init__":{
  "__set__":true,
  "elements":[
   "pytest-workflow-1.2.0-py_0",
   "pytest-workflow-1.2.1-py_0",
   "pytest-workflow-1.2.2-py_0",
   "pytest-workflow-1.3.0-py_0",
   "pytest-workflow-1.5.0-pyhd8ed1ab_0"
  ]
 },
 "pytest_workflow.plugin.WorkflowTestsCollector.collect":{
  "__set__":true,
  "elements":[
   "pytest-workflow-1.2.0-py_0",
   "pytest-workflow-1.2.1-py_0",
   "pytest-workflow-1.2.2-py_0",
   "pytest-workflow-1.3.0-py_0",
   "pytest-workflow-1.5.0-pyhd8ed1ab_0"
  ]
 },
 "pytest_workflow.plugin.WorkflowTestsCollector.queue_workflow":{
  "__set__":true,
  "elements":[
   "pytest-workflow-1.2.0-py_0",
   "pytest-workflow-1.2.1-py_0",
   "pytest-workflow-1.2.2-py_0",
   "pytest-workflow-1.3.0-py_0",
   "pytest-workflow-1.5.0-pyhd8ed1ab_0"
  ]
 },
 "pytest_workflow.plugin.YamlFile":{
  "__set__":true,
  "elements":[
   "pytest-workflow-1.2.0-py_0",
   "pytest-workflow-1.2.1-py_0",
   "pytest-workflow-1.2.2-py_0",
   "pytest-workflow-1.3.0-py_0",
   "pytest-workflow-1.5.0-pyhd8ed1ab_0"
  ]
 },
 "pytest_workflow.plugin.YamlFile.__init__":{
  "__set__":true,
  "elements":[
   "pytest-workflow-1.2.0-py_0",
   "pytest-workflow-1.2.1-py_0",
   "pytest-workflow-1.2.2-py_0"
  ]
 },
 "pytest_workflow.plugin.YamlFile.collect":{
  "__set__":true,
  "elements":[
   "pytest-workflow-1.2.0-py_0",
   "pytest-workflow-1.2.1-py_0",
   "pytest-workflow-1.2.2-py_0",
   "pytest-workflow-1.3.0-py_0",
   "pytest-workflow-1.5.0-pyhd8ed1ab_0"
  ]
 },
 "pytest_workflow.plugin.__pytest_workflow_cli":{
  "__set__":true,
  "elements":[
   "pytest-workflow-1.3.0-py_0",
   "pytest-workflow-1.5.0-pyhd8ed1ab_0"
  ]
 },
 "pytest_workflow.plugin.__pytest_workflow_cli.ArgParser":{
  "__set__":true,
  "elements":[
   "pytest-workflow-1.3.0-py_0",
   "pytest-workflow-1.5.0-pyhd8ed1ab_0"
  ]
 },
 "pytest_workflow.plugin.__pytest_workflow_cli.ArgParser.addoption":{
  "__set__":true,
  "elements":[
   "pytest-workflow-1.3.0-py_0",
   "pytest-workflow-1.5.0-pyhd8ed1ab_0"
  ]
 },
 "pytest_workflow.plugin.get_workflow_names_from_workflow_marker":{
  "__set__":true,
  "elements":[
   "pytest-workflow-1.3.0-py_0",
   "pytest-workflow-1.5.0-pyhd8ed1ab_0"
  ]
 },
 "pytest_workflow.plugin.pytest_addoption":{
  "__set__":true,
  "elements":[
   "pytest-workflow-1.2.0-py_0",
   "pytest-workflow-1.2.1-py_0",
   "pytest-workflow-1.2.2-py_0",
   "pytest-workflow-1.3.0-py_0",
   "pytest-workflow-1.5.0-pyhd8ed1ab_0"
  ]
 },
 "pytest_workflow.plugin.pytest_collect_file":{
  "__set__":true,
  "elements":[
   "pytest-workflow-1.2.0-py_0",
   "pytest-workflow-1.2.1-py_0",
   "pytest-workflow-1.2.2-py_0",
   "pytest-workflow-1.3.0-py_0",
   "pytest-workflow-1.5.0-pyhd8ed1ab_0"
  ]
 },
 "pytest_workflow.plugin.pytest_collection":{
  "__set__":true,
  "elements":[
   "pytest-workflow-1.2.0-py_0",
   "pytest-workflow-1.2.1-py_0",
   "pytest-workflow-1.2.2-py_0",
   "pytest-workflow-1.3.0-py_0",
   "pytest-workflow-1.5.0-pyhd8ed1ab_0"
  ]
 },
 "pytest_workflow.plugin.pytest_collection_modifyitems":{
  "__set__":true,
  "elements":[
   "pytest-workflow-1.2.0-py_0",
   "pytest-workflow-1.2.1-py_0",
   "pytest-workflow-1.2.2-py_0",
   "pytest-workflow-1.3.0-py_0",
   "pytest-workflow-1.5.0-pyhd8ed1ab_0"
  ]
 },
 "pytest_workflow.plugin.pytest_collectstart":{
  "__set__":true,
  "elements":[
   "pytest-workflow-1.2.2-py_0",
   "pytest-workflow-1.3.0-py_0",
   "pytest-workflow-1.5.0-pyhd8ed1ab_0"
  ]
 },
 "pytest_workflow.plugin.pytest_configure":{
  "__set__":true,
  "elements":[
   "pytest-workflow-1.2.0-py_0",
   "pytest-workflow-1.2.1-py_0",
   "pytest-workflow-1.2.2-py_0",
   "pytest-workflow-1.3.0-py_0",
   "pytest-workflow-1.5.0-pyhd8ed1ab_0"
  ]
 },
 "pytest_workflow.plugin.pytest_generate_tests":{
  "__set__":true,
  "elements":[
   "pytest-workflow-1.3.0-py_0",
   "pytest-workflow-1.5.0-pyhd8ed1ab_0"
  ]
 },
 "pytest_workflow.plugin.pytest_runtestloop":{
  "__set__":true,
  "elements":[
   "pytest-workflow-1.2.0-py_0",
   "pytest-workflow-1.2.1-py_0",
   "pytest-workflow-1.2.2-py_0",
   "pytest-workflow-1.3.0-py_0",
   "pytest-workflow-1.5.0-pyhd8ed1ab_0"
  ]
 },
 "pytest_workflow.plugin.pytest_sessionfinish":{
  "__set__":true,
  "elements":[
   "pytest-workflow-1.2.0-py_0",
   "pytest-workflow-1.2.1-py_0",
   "pytest-workflow-1.2.2-py_0",
   "pytest-workflow-1.3.0-py_0",
   "pytest-workflow-1.5.0-pyhd8ed1ab_0"
  ]
 },
 "pytest_workflow.plugin.workflow_dir":{
  "__set__":true,
  "elements":[
   "pytest-workflow-1.2.0-py_0",
   "pytest-workflow-1.2.1-py_0",
   "pytest-workflow-1.2.2-py_0"
  ]
 },
 "pytest_workflow.replace_whitespace":{
  "__set__":true,
  "elements":[
   "pytest-workflow-1.2.0-py_0",
   "pytest-workflow-1.2.1-py_0",
   "pytest-workflow-1.2.2-py_0"
  ]
 },
 "pytest_workflow.rm_dirs":{
  "__set__":true,
  "elements":[
   "pytest-workflow-1.2.0-py_0",
   "pytest-workflow-1.2.1-py_0",
   "pytest-workflow-1.2.2-py_0"
  ]
 },
 "pytest_workflow.schema":{
  "__set__":true,
  "elements":[
   "pytest-workflow-1.2.0-py_0",
   "pytest-workflow-1.2.1-py_0",
   "pytest-workflow-1.2.2-py_0",
   "pytest-workflow-1.3.0-py_0",
   "pytest-workflow-1.5.0-pyhd8ed1ab_0"
  ]
 },
 "pytest_workflow.schema.ContentTest":{
  "__set__":true,
  "elements":[
   "pytest-workflow-1.2.0-py_0",
   "pytest-workflow-1.2.1-py_0",
   "pytest-workflow-1.2.2-py_0",
   "pytest-workflow-1.3.0-py_0",
   "pytest-workflow-1.5.0-pyhd8ed1ab_0"
  ]
 },
 "pytest_workflow.schema.ContentTest.__init__":{
  "__set__":true,
  "elements":[
   "pytest-workflow-1.2.0-py_0",
   "pytest-workflow-1.2.1-py_0",
   "pytest-workflow-1.2.2-py_0",
   "pytest-workflow-1.3.0-py_0",
   "pytest-workflow-1.5.0-pyhd8ed1ab_0"
  ]
 },
 "pytest_workflow.schema.ContentTest.from_dict":{
  "__set__":true,
  "elements":[
   "pytest-workflow-1.2.0-py_0",
   "pytest-workflow-1.2.1-py_0",
   "pytest-workflow-1.2.2-py_0"
  ]
 },
 "pytest_workflow.schema.FileTest":{
  "__set__":true,
  "elements":[
   "pytest-workflow-1.2.0-py_0",
   "pytest-workflow-1.2.1-py_0",
   "pytest-workflow-1.2.2-py_0",
   "pytest-workflow-1.3.0-py_0",
   "pytest-workflow-1.5.0-pyhd8ed1ab_0"
  ]
 },
 "pytest_workflow.schema.FileTest.__init__":{
  "__set__":true,
  "elements":[
   "pytest-workflow-1.2.0-py_0",
   "pytest-workflow-1.2.1-py_0",
   "pytest-workflow-1.2.2-py_0",
   "pytest-workflow-1.3.0-py_0",
   "pytest-workflow-1.5.0-pyhd8ed1ab_0"
  ]
 },
 "pytest_workflow.schema.FileTest.from_dict":{
  "__set__":true,
  "elements":[
   "pytest-workflow-1.2.0-py_0",
   "pytest-workflow-1.2.1-py_0",
   "pytest-workflow-1.2.2-py_0"
  ]
 },
 "pytest_workflow.schema.WorkflowTest":{
  "__set__":true,
  "elements":[
   "pytest-workflow-1.2.0-py_0",
   "pytest-workflow-1.2.1-py_0",
   "pytest-workflow-1.2.2-py_0",
   "pytest-workflow-1.3.0-py_0",
   "pytest-workflow-1.5.0-pyhd8ed1ab_0"
  ]
 },
 "pytest_workflow.schema.WorkflowTest.__init__":{
  "__set__":true,
  "elements":[
   "pytest-workflow-1.2.0-py_0",
   "pytest-workflow-1.2.1-py_0",
   "pytest-workflow-1.2.2-py_0",
   "pytest-workflow-1.3.0-py_0",
   "pytest-workflow-1.5.0-pyhd8ed1ab_0"
  ]
 },
 "pytest_workflow.schema.WorkflowTest.from_schema":{
  "__set__":true,
  "elements":[
   "pytest-workflow-1.2.0-py_0",
   "pytest-workflow-1.2.1-py_0",
   "pytest-workflow-1.2.2-py_0",
   "pytest-workflow-1.3.0-py_0",
   "pytest-workflow-1.5.0-pyhd8ed1ab_0"
  ]
 },
 "pytest_workflow.schema.validate_schema":{
  "__set__":true,
  "elements":[
   "pytest-workflow-1.2.0-py_0",
   "pytest-workflow-1.2.1-py_0",
   "pytest-workflow-1.2.2-py_0",
   "pytest-workflow-1.3.0-py_0",
   "pytest-workflow-1.5.0-pyhd8ed1ab_0"
  ]
 },
 "pytest_workflow.schema.validate_schema.test_contains_concordance":{
  "__set__":true,
  "elements":[
   "pytest-workflow-1.2.0-py_0",
   "pytest-workflow-1.2.1-py_0",
   "pytest-workflow-1.2.2-py_0",
   "pytest-workflow-1.3.0-py_0",
   "pytest-workflow-1.5.0-pyhd8ed1ab_0"
  ]
 },
 "pytest_workflow.schema.workflow_tests_from_schema":{
  "__set__":true,
  "elements":[
   "pytest-workflow-1.2.0-py_0",
   "pytest-workflow-1.2.1-py_0",
   "pytest-workflow-1.2.2-py_0",
   "pytest-workflow-1.3.0-py_0",
   "pytest-workflow-1.5.0-pyhd8ed1ab_0"
  ]
 },
 "pytest_workflow.util":{
  "__set__":true,
  "elements":[
   "pytest-workflow-1.3.0-py_0",
   "pytest-workflow-1.5.0-pyhd8ed1ab_0"
  ]
 },
 "pytest_workflow.util.file_md5sum":{
  "__set__":true,
  "elements":[
   "pytest-workflow-1.5.0-pyhd8ed1ab_0"
  ]
 },
 "pytest_workflow.util.is_in_dir":{
  "__set__":true,
  "elements":[
   "pytest-workflow-1.3.0-py_0",
   "pytest-workflow-1.5.0-pyhd8ed1ab_0"
  ]
 },
 "pytest_workflow.util.link_tree":{
  "__set__":true,
  "elements":[
   "pytest-workflow-1.3.0-py_0",
   "pytest-workflow-1.5.0-pyhd8ed1ab_0"
  ]
 },
 "pytest_workflow.util.replace_whitespace":{
  "__set__":true,
  "elements":[
   "pytest-workflow-1.3.0-py_0",
   "pytest-workflow-1.5.0-pyhd8ed1ab_0"
  ]
 },
 "pytest_workflow.util.rm_dirs":{
  "__set__":true,
  "elements":[
   "pytest-workflow-1.3.0-py_0"
  ]
 },
 "pytest_workflow.workflow":{
  "__set__":true,
  "elements":[
   "pytest-workflow-1.2.0-py_0",
   "pytest-workflow-1.2.1-py_0",
   "pytest-workflow-1.2.2-py_0",
   "pytest-workflow-1.3.0-py_0",
   "pytest-workflow-1.5.0-pyhd8ed1ab_0"
  ]
 },
 "pytest_workflow.workflow.Workflow":{
  "__set__":true,
  "elements":[
   "pytest-workflow-1.2.0-py_0",
   "pytest-workflow-1.2.1-py_0",
   "pytest-workflow-1.2.2-py_0",
   "pytest-workflow-1.3.0-py_0",
   "pytest-workflow-1.5.0-pyhd8ed1ab_0"
  ]
 },
 "pytest_workflow.workflow.Workflow.__init__":{
  "__set__":true,
  "elements":[
   "pytest-workflow-1.2.0-py_0",
   "pytest-workflow-1.2.1-py_0",
   "pytest-workflow-1.2.2-py_0",
   "pytest-workflow-1.3.0-py_0",
   "pytest-workflow-1.5.0-pyhd8ed1ab_0"
  ]
 },
 "pytest_workflow.workflow.Workflow.exit_code":{
  "__set__":true,
  "elements":[
   "pytest-workflow-1.2.0-py_0",
   "pytest-workflow-1.2.1-py_0",
   "pytest-workflow-1.2.2-py_0",
   "pytest-workflow-1.3.0-py_0",
   "pytest-workflow-1.5.0-pyhd8ed1ab_0"
  ]
 },
 "pytest_workflow.workflow.Workflow.run":{
  "__set__":true,
  "elements":[
   "pytest-workflow-1.2.0-py_0",
   "pytest-workflow-1.2.1-py_0",
   "pytest-workflow-1.2.2-py_0",
   "pytest-workflow-1.3.0-py_0",
   "pytest-workflow-1.5.0-pyhd8ed1ab_0"
  ]
 },
 "pytest_workflow.workflow.Workflow.start":{
  "__set__":true,
  "elements":[
   "pytest-workflow-1.2.0-py_0",
   "pytest-workflow-1.2.1-py_0",
   "pytest-workflow-1.2.2-py_0",
   "pytest-workflow-1.3.0-py_0",
   "pytest-workflow-1.5.0-pyhd8ed1ab_0"
  ]
 },
 "pytest_workflow.workflow.Workflow.stderr":{
  "__set__":true,
  "elements":[
   "pytest-workflow-1.2.0-py_0",
   "pytest-workflow-1.2.1-py_0",
   "pytest-workflow-1.2.2-py_0",
   "pytest-workflow-1.3.0-py_0",
   "pytest-workflow-1.5.0-pyhd8ed1ab_0"
  ]
 },
 "pytest_workflow.workflow.Workflow.stdout":{
  "__set__":true,
  "elements":[
   "pytest-workflow-1.2.0-py_0",
   "pytest-workflow-1.2.1-py_0",
   "pytest-workflow-1.2.2-py_0",
   "pytest-workflow-1.3.0-py_0",
   "pytest-workflow-1.5.0-pyhd8ed1ab_0"
  ]
 },
 "pytest_workflow.workflow.Workflow.wait":{
  "__set__":true,
  "elements":[
   "pytest-workflow-1.2.0-py_0",
   "pytest-workflow-1.2.1-py_0",
   "pytest-workflow-1.2.2-py_0",
   "pytest-workflow-1.3.0-py_0",
   "pytest-workflow-1.5.0-pyhd8ed1ab_0"
  ]
 },
 "pytest_workflow.workflow.WorkflowQueue":{
  "__set__":true,
  "elements":[
   "pytest-workflow-1.2.0-py_0",
   "pytest-workflow-1.2.1-py_0",
   "pytest-workflow-1.2.2-py_0",
   "pytest-workflow-1.3.0-py_0",
   "pytest-workflow-1.5.0-pyhd8ed1ab_0"
  ]
 },
 "pytest_workflow.workflow.WorkflowQueue.__init__":{
  "__set__":true,
  "elements":[
   "pytest-workflow-1.2.0-py_0",
   "pytest-workflow-1.2.1-py_0",
   "pytest-workflow-1.2.2-py_0",
   "pytest-workflow-1.3.0-py_0",
   "pytest-workflow-1.5.0-pyhd8ed1ab_0"
  ]
 },
 "pytest_workflow.workflow.WorkflowQueue.process":{
  "__set__":true,
  "elements":[
   "pytest-workflow-1.2.0-py_0",
   "pytest-workflow-1.2.1-py_0",
   "pytest-workflow-1.2.2-py_0",
   "pytest-workflow-1.3.0-py_0",
   "pytest-workflow-1.5.0-pyhd8ed1ab_0"
  ]
 },
 "pytest_workflow.workflow.WorkflowQueue.put":{
  "__set__":true,
  "elements":[
   "pytest-workflow-1.2.0-py_0",
   "pytest-workflow-1.2.1-py_0",
   "pytest-workflow-1.2.2-py_0",
   "pytest-workflow-1.3.0-py_0",
   "pytest-workflow-1.5.0-pyhd8ed1ab_0"
  ]
 },
 "pytest_workflow.workflow.WorkflowQueue.worker":{
  "__set__":true,
  "elements":[
   "pytest-workflow-1.2.0-py_0",
   "pytest-workflow-1.2.1-py_0",
   "pytest-workflow-1.2.2-py_0",
   "pytest-workflow-1.3.0-py_0",
   "pytest-workflow-1.5.0-pyhd8ed1ab_0"
  ]
 }
}