{
 "aiida_cusp": {
  "lineno": null,
  "symbols_in_volume": [],
  "type": "module"
 },
 "aiida_cusp.calculators": {
  "lineno": null,
  "symbols_in_volume": [],
  "type": "module"
 },
 "aiida_cusp.calculators.calculation_base": {
  "lineno": null,
  "symbols_in_volume": [],
  "type": "module"
 },
 "aiida_cusp.calculators.calculation_base.CalculationBase": {
  "lineno": 36,
  "symbols_in_volume": [
   "aiida.engine.CalcJob",
   "aiida_cusp.utils.defaults.PluginDefaults.STDERR_FNAME",
   "aiida_cusp.utils.defaults.PluginDefaults.STDOUT_FNAME"
  ],
  "type": "class"
 },
 "aiida_cusp.calculators.calculation_base.CalculationBase.create_calculation_inputs": {
  "lineno": 341,
  "symbols_in_volume": [],
  "type": "function"
 },
 "aiida_cusp.calculators.calculation_base.CalculationBase.define": {
  "lineno": 47,
  "symbols_in_volume": [
   "aiida.orm.Bool",
   "aiida.orm.Code",
   "aiida.orm.Dict",
   "aiida.orm.List",
   "aiida.orm.RemoteData",
   "aiida.orm.nodes.data.base.to_aiida_type",
   "aiida_cusp.utils.defaults.PluginDefaults.PARSER_OUTPUT_NAMESPACE"
  ],
  "type": "function"
 },
 "aiida_cusp.calculators.calculation_base.CalculationBase.prepare_for_submission": {
  "lineno": 120,
  "symbols_in_volume": [
   "aiida.common.CalcInfo",
   "aiida.common.CodeInfo",
   "aiida.common.CodeRunMode.SERIAL",
   "aiida_cusp.utils.defaults.PluginDefaults.CSTDN_SPEC_FNAME"
  ],
  "type": "function"
 },
 "aiida_cusp.calculators.calculation_base.CalculationBase.remote_filelist": {
  "lineno": 206,
  "symbols_in_volume": [
   "pathlib.Path"
  ],
  "type": "function"
 },
 "aiida_cusp.calculators.calculation_base.CalculationBase.restart_copy_remote": {
  "lineno": 270,
  "symbols_in_volume": [
   "aiida_cusp.utils.defaults.VaspDefaults.FNAMES",
   "pathlib.Path"
  ],
  "type": "function"
 },
 "aiida_cusp.calculators.calculation_base.CalculationBase.restart_files_exclude": {
  "lineno": 230,
  "symbols_in_volume": [
   "aiida_cusp.utils.defaults.PluginDefaults.CSTDN_SPEC_FNAME",
   "aiida_cusp.utils.defaults.VaspDefaults.FNAMES"
  ],
  "type": "function"
 },
 "aiida_cusp.calculators.calculation_base.CalculationBase.retrieve_permanent_list": {
  "lineno": 316,
  "symbols_in_volume": [
   "aiida_cusp.utils.defaults.CustodianDefaults.RUN_LOG_FNAME",
   "aiida_cusp.utils.defaults.PluginDefaults.CSTDN_SPEC_FNAME",
   "aiida_cusp.utils.defaults.PluginDefaults.STDERR_FNAME",
   "aiida_cusp.utils.defaults.PluginDefaults.STDOUT_FNAME"
  ],
  "type": "function"
 },
 "aiida_cusp.calculators.calculation_base.CalculationBase.retrieve_temporary_list": {
  "lineno": 303,
  "symbols_in_volume": [],
  "type": "function"
 },
 "aiida_cusp.calculators.calculation_base.CalculationBase.setup_custodian_settings": {
  "lineno": 250,
  "symbols_in_volume": [
   "aiida_cusp.utils.custodian.CustodianSettings"
  ],
  "type": "function"
 },
 "aiida_cusp.calculators.calculation_base.CalculationBase.vasp_calc_mpi_args": {
  "lineno": 162,
  "symbols_in_volume": [],
  "type": "function"
 },
 "aiida_cusp.calculators.calculation_base.CalculationBase.vasp_run_line": {
  "lineno": 184,
  "symbols_in_volume": [],
  "type": "function"
 },
 "aiida_cusp.calculators.calculation_base.lidi_serializer": {
  "lineno": 23,
  "symbols_in_volume": [
   "aiida.orm.Dict"
  ],
  "type": "function"
 },
 "aiida_cusp.calculators.vasp_basic_calculation": {
  "lineno": null,
  "symbols_in_volume": [],
  "type": "module"
 },
 "aiida_cusp.calculators.vasp_basic_calculation.VaspBasicCalculation": {
  "lineno": 19,
  "symbols_in_volume": [
   "aiida_cusp.calculators.calculation_base.CalculationBase"
  ],
  "type": "class"
 },
 "aiida_cusp.calculators.vasp_basic_calculation.VaspBasicCalculation.__create_inputs_for_regular_run": {
  "lineno": 55,
  "symbols_in_volume": [],
  "type": "function"
 },
 "aiida_cusp.calculators.vasp_basic_calculation.VaspBasicCalculation.__create_inputs_for_restart_run": {
  "lineno": 67,
  "symbols_in_volume": [],
  "type": "function"
 },
 "aiida_cusp.calculators.vasp_basic_calculation.VaspBasicCalculation.__verify_regular_inputs": {
  "lineno": 86,
  "symbols_in_volume": [],
  "type": "function"
 },
 "aiida_cusp.calculators.vasp_basic_calculation.VaspBasicCalculation.__verify_restart_inputs": {
  "lineno": 105,
  "symbols_in_volume": [],
  "type": "function"
 },
 "aiida_cusp.calculators.vasp_basic_calculation.VaspBasicCalculation.__write_custodian_spec": {
  "lineno": 151,
  "symbols_in_volume": [
   "aiida_cusp.utils.defaults.PluginDefaults.CSTDN_SPEC_FNAME",
   "pathlib.Path"
  ],
  "type": "function"
 },
 "aiida_cusp.calculators.vasp_basic_calculation.VaspBasicCalculation.__write_incar": {
  "lineno": 119,
  "symbols_in_volume": [
   "aiida_cusp.utils.defaults.VaspDefaults.FNAMES"
  ],
  "type": "function"
 },
 "aiida_cusp.calculators.vasp_basic_calculation.VaspBasicCalculation.__write_kpoints": {
  "lineno": 126,
  "symbols_in_volume": [
   "aiida_cusp.utils.defaults.VaspDefaults.FNAMES"
  ],
  "type": "function"
 },
 "aiida_cusp.calculators.vasp_basic_calculation.VaspBasicCalculation.__write_poscar": {
  "lineno": 133,
  "symbols_in_volume": [
   "aiida_cusp.utils.defaults.VaspDefaults.FNAMES"
  ],
  "type": "function"
 },
 "aiida_cusp.calculators.vasp_basic_calculation.VaspBasicCalculation.__write_potcar": {
  "lineno": 140,
  "symbols_in_volume": [
   "aiida_cusp.data.VaspPotcarData.potcar_from_linklist",
   "aiida_cusp.utils.defaults.VaspDefaults.FNAMES"
  ],
  "type": "function"
 },
 "aiida_cusp.calculators.vasp_basic_calculation.VaspBasicCalculation.create_calculation_inputs": {
  "lineno": 43,
  "symbols_in_volume": [],
  "type": "function"
 },
 "aiida_cusp.calculators.vasp_basic_calculation.VaspBasicCalculation.define": {
  "lineno": 29,
  "symbols_in_volume": [
   "aiida_cusp.data.VaspPoscarData"
  ],
  "type": "function"
 },
 "aiida_cusp.calculators.vasp_calculation": {
  "lineno": null,
  "symbols_in_volume": [],
  "type": "module"
 },
 "aiida_cusp.calculators.vasp_calculation.VaspCalculation": {
  "lineno": 15,
  "symbols_in_volume": [
   "aiida_cusp.calculators.vasp_basic_calculation.VaspBasicCalculation",
   "aiida_cusp.calculators.vasp_neb_calculation.VaspNebCalculation"
  ],
  "type": "class"
 },
 "aiida_cusp.calculators.vasp_calculation.VaspCalculation.create_calculation_inputs": {
  "lineno": 76,
  "symbols_in_volume": [
   "aiida_cusp.calculators.vasp_basic_calculation.VaspBasicCalculation",
   "aiida_cusp.calculators.vasp_neb_calculation.VaspNebCalculation"
  ],
  "type": "function"
 },
 "aiida_cusp.calculators.vasp_calculation.VaspCalculation.define": {
  "lineno": 19,
  "symbols_in_volume": [
   "aiida_cusp.data.VaspIncarData",
   "aiida_cusp.data.VaspKpointData",
   "aiida_cusp.data.VaspPotcarData"
  ],
  "type": "function"
 },
 "aiida_cusp.calculators.vasp_calculation.VaspCalculation.is_neb": {
  "lineno": 111,
  "symbols_in_volume": [],
  "type": "function"
 },
 "aiida_cusp.calculators.vasp_calculation.VaspCalculation.restart_files_exclude": {
  "lineno": 91,
  "symbols_in_volume": [
   "aiida_cusp.utils.defaults.VaspDefaults.FNAMES"
  ],
  "type": "function"
 },
 "aiida_cusp.calculators.vasp_calculation.VaspCalculation.verify_structure_inputs": {
  "lineno": 125,
  "symbols_in_volume": [],
  "type": "function"
 },
 "aiida_cusp.calculators.vasp_neb_calculation": {
  "lineno": null,
  "symbols_in_volume": [],
  "type": "module"
 },
 "aiida_cusp.calculators.vasp_neb_calculation.VaspNebCalculation": {
  "lineno": 20,
  "symbols_in_volume": [
   "aiida_cusp.calculators.calculation_base.CalculationBase"
  ],
  "type": "class"
 },
 "aiida_cusp.calculators.vasp_neb_calculation.VaspNebCalculation.__create_inputs_for_regular_run": {
  "lineno": 68,
  "symbols_in_volume": [],
  "type": "function"
 },
 "aiida_cusp.calculators.vasp_neb_calculation.VaspNebCalculation.__create_inputs_for_restart_run": {
  "lineno": 80,
  "symbols_in_volume": [],
  "type": "function"
 },
 "aiida_cusp.calculators.vasp_neb_calculation.VaspNebCalculation.__verify_regular_inputs": {
  "lineno": 99,
  "symbols_in_volume": [
   "aiida_cusp.utils.defaults.PluginDefaults.NEB_NODE_PREFIX",
   "aiida_cusp.utils.defaults.PluginDefaults.NEB_NODE_REGEX"
  ],
  "type": "function"
 },
 "aiida_cusp.calculators.vasp_neb_calculation.VaspNebCalculation.__verify_restart_inputs": {
  "lineno": 128,
  "symbols_in_volume": [],
  "type": "function"
 },
 "aiida_cusp.calculators.vasp_neb_calculation.VaspNebCalculation.__write_custodian_spec": {
  "lineno": 185,
  "symbols_in_volume": [
   "aiida_cusp.utils.defaults.PluginDefaults.CSTDN_SPEC_FNAME",
   "pathlib.Path"
  ],
  "type": "function"
 },
 "aiida_cusp.calculators.vasp_neb_calculation.VaspNebCalculation.__write_incar": {
  "lineno": 142,
  "symbols_in_volume": [
   "aiida_cusp.utils.defaults.VaspDefaults.FNAMES"
  ],
  "type": "function"
 },
 "aiida_cusp.calculators.vasp_neb_calculation.VaspNebCalculation.__write_kpoints": {
  "lineno": 149,
  "symbols_in_volume": [
   "aiida_cusp.utils.defaults.VaspDefaults.FNAMES"
  ],
  "type": "function"
 },
 "aiida_cusp.calculators.vasp_neb_calculation.VaspNebCalculation.__write_neb_path": {
  "lineno": 169,
  "symbols_in_volume": [
   "aiida_cusp.utils.defaults.PluginDefaults.NEB_NODE_PREFIX",
   "aiida_cusp.utils.defaults.VaspDefaults.FNAMES",
   "pathlib.Path",
   "re.sub"
  ],
  "type": "function"
 },
 "aiida_cusp.calculators.vasp_neb_calculation.VaspNebCalculation.__write_potcar": {
  "lineno": 156,
  "symbols_in_volume": [
   "aiida_cusp.data.VaspPotcarData.potcar_from_linklist",
   "aiida_cusp.utils.defaults.PluginDefaults.NEB_NODE_PREFIX",
   "aiida_cusp.utils.defaults.VaspDefaults.FNAMES"
  ],
  "type": "function"
 },
 "aiida_cusp.calculators.vasp_neb_calculation.VaspNebCalculation.create_calculation_inputs": {
  "lineno": 56,
  "symbols_in_volume": [],
  "type": "function"
 },
 "aiida_cusp.calculators.vasp_neb_calculation.VaspNebCalculation.define": {
  "lineno": 31,
  "symbols_in_volume": [
   "aiida_cusp.data.VaspPoscarData"
  ],
  "type": "function"
 },
 "aiida_cusp.cli": {
  "lineno": null,
  "symbols_in_volume": [],
  "type": "module"
 },
 "aiida_cusp.cli.potcar_cmd": {
  "lineno": null,
  "symbols_in_volume": [],
  "type": "module"
 },
 "aiida_cusp.cli.potcar_cmd.add_potcar": {
  "lineno": 24,
  "symbols_in_volume": [],
  "type": "function"
 },
 "aiida_cusp.cli.potcar_cmd.add_potcar_family": {
  "lineno": 32,
  "symbols_in_volume": [
   "aiida_cusp.data.inputs.vasp_potcar.VaspPotcarFile.add_potential",
   "aiida_cusp.utils.defaults.VaspDefaults.FNAMES",
   "aiida_cusp.utils.exceptions.CommandLineError",
   "aiida_cusp.utils.exceptions.MultiplePotcarError",
   "aiida_cusp.utils.exceptions.VaspPotcarFileError",
   "aiida_cusp.utils.potcar.PotcarPathParser",
   "click.Path",
   "click.argument",
   "click.confirm",
   "click.echo",
   "pathlib.Path",
   "tabulate.tabulate",
   "warnings.warn"
  ],
  "type": "function"
 },
 "aiida_cusp.cli.potcar_cmd.add_potcar_single": {
  "lineno": 151,
  "symbols_in_volume": [
   "aiida_cusp.data.inputs.vasp_potcar.VaspPotcarFile.add_potential",
   "aiida_cusp.utils.defaults.VaspDefaults.FNAMES",
   "aiida_cusp.utils.exceptions.CommandLineError",
   "aiida_cusp.utils.exceptions.MultiplePotcarError",
   "aiida_cusp.utils.exceptions.VaspPotcarFileError",
   "click.Path",
   "click.argument",
   "click.confirm",
   "click.echo",
   "click.option",
   "pathlib.Path",
   "tabulate.tabulate",
   "warnings.warn"
  ],
  "type": "function"
 },
 "aiida_cusp.cli.potcar_cmd.list_potcar": {
  "lineno": 265,
  "symbols_in_volume": [
   "aiida_cusp.data.inputs.vasp_potcar.VaspPotcarFile.from_tags",
   "click.echo",
   "click.option",
   "tabulate.tabulate"
  ],
  "type": "function"
 },
 "aiida_cusp.cli.potcar_cmd.potcar": {
  "lineno": 16,
  "symbols_in_volume": [
   "aiida.cmdline.commands.cmd_data.verdi_data.group"
  ],
  "type": "function"
 },
 "aiida_cusp.cli.potcar_cmd.show_potcar": {
  "lineno": 320,
  "symbols_in_volume": [
   "aiida.orm.load_node",
   "aiida_cusp.utils.exceptions.CommandLineError",
   "click.argument",
   "click.echo",
   "click.option",
   "re.search"
  ],
  "type": "function"
 },
 "aiida_cusp.data": {
  "lineno": null,
  "symbols_in_volume": [],
  "type": "module"
 },
 "aiida_cusp.data.inputs": {
  "lineno": null,
  "symbols_in_volume": [],
  "type": "module"
 },
 "aiida_cusp.data.inputs.vasp_incar": {
  "lineno": null,
  "symbols_in_volume": [],
  "type": "module"
 },
 "aiida_cusp.data.inputs.vasp_incar.IncarWrapper": {
  "lineno": 69,
  "symbols_in_volume": [],
  "type": "class"
 },
 "aiida_cusp.data.inputs.vasp_incar.IncarWrapper.__new__": {
  "lineno": 85,
  "symbols_in_volume": [
   "aiida_cusp.utils.exceptions.IncarWrapperError",
   "pymatgen.io.vasp.inputs.Incar"
  ],
  "type": "function"
 },
 "aiida_cusp.data.inputs.vasp_incar.IncarWrapper.keys_to_upper_case": {
  "lineno": 99,
  "symbols_in_volume": [],
  "type": "function"
 },
 "aiida_cusp.data.inputs.vasp_incar.VaspIncarData": {
  "lineno": 16,
  "symbols_in_volume": [
   "aiida.orm.Dict"
  ],
  "type": "class"
 },
 "aiida_cusp.data.inputs.vasp_incar.VaspIncarData.__init__": {
  "lineno": 29,
  "symbols_in_volume": [],
  "type": "function"
 },
 "aiida_cusp.data.inputs.vasp_incar.VaspIncarData.get_incar": {
  "lineno": 39,
  "symbols_in_volume": [
   "pymatgen.io.vasp.inputs.Incar.from_dict"
  ],
  "type": "function"
 },
 "aiida_cusp.data.inputs.vasp_incar.VaspIncarData.write_file": {
  "lineno": 51,
  "symbols_in_volume": [],
  "type": "function"
 },
 "aiida_cusp.data.inputs.vasp_kpoint": {
  "lineno": null,
  "symbols_in_volume": [],
  "type": "module"
 },
 "aiida_cusp.data.inputs.vasp_kpoint.KpointWrapper": {
  "lineno": 90,
  "symbols_in_volume": [],
  "type": "class"
 },
 "aiida_cusp.data.inputs.vasp_kpoint.KpointWrapper.__new__": {
  "lineno": 129,
  "symbols_in_volume": [
   "pymatgen.io.vasp.inputs.Kpoints"
  ],
  "type": "function"
 },
 "aiida_cusp.data.inputs.vasp_kpoint.KpointWrapper.auto_int": {
  "lineno": 210,
  "symbols_in_volume": [
   "pymatgen.io.vasp.inputs.Kpoints.automatic",
   "warnings.warn"
  ],
  "type": "function"
 },
 "aiida_cusp.data.inputs.vasp_kpoint.KpointWrapper.build_init_mode": {
  "lineno": 182,
  "symbols_in_volume": [],
  "type": "function"
 },
 "aiida_cusp.data.inputs.vasp_kpoint.KpointWrapper.complete_parameter_list": {
  "lineno": 155,
  "symbols_in_volume": [
   "aiida_cusp.utils.exceptions.KpointWrapperError"
  ],
  "type": "function"
 },
 "aiida_cusp.data.inputs.vasp_kpoint.KpointWrapper.gamma_float": {
  "lineno": 285,
  "symbols_in_volume": [
   "aiida_cusp.utils.exceptions.KpointWrapperError",
   "pymatgen.io.vasp.inputs.Kpoints.automatic_density",
   "warnings.warn"
  ],
  "type": "function"
 },
 "aiida_cusp.data.inputs.vasp_kpoint.KpointWrapper.gamma_list": {
  "lineno": 231,
  "symbols_in_volume": [
   "aiida_cusp.utils.exceptions.KpointWrapperError",
   "pymatgen.io.vasp.inputs.Kpoints.gamma_automatic",
   "warnings.warn"
  ],
  "type": "function"
 },
 "aiida_cusp.data.inputs.vasp_kpoint.KpointWrapper.line_int": {
  "lineno": 334,
  "symbols_in_volume": [
   "aiida_cusp.utils.exceptions.KpointWrapperError",
   "pymatgen.io.vasp.inputs.Kpoints.automatic_linemode",
   "warnings.warn"
  ],
  "type": "function"
 },
 "aiida_cusp.data.inputs.vasp_kpoint.KpointWrapper.monkhorst_float": {
  "lineno": 309,
  "symbols_in_volume": [
   "aiida_cusp.utils.exceptions.KpointWrapperError",
   "pymatgen.io.vasp.inputs.Kpoints.automatic_density",
   "warnings.warn"
  ],
  "type": "function"
 },
 "aiida_cusp.data.inputs.vasp_kpoint.KpointWrapper.monkhorst_list": {
  "lineno": 257,
  "symbols_in_volume": [
   "aiida_cusp.utils.exceptions.KpointWrapperError",
   "pymatgen.io.vasp.inputs.Kpoints.monkhorst_automatic",
   "warnings.warn"
  ],
  "type": "function"
 },
 "aiida_cusp.data.inputs.vasp_kpoint.KpointWrapper.structure_from_input": {
  "lineno": 194,
  "symbols_in_volume": [
   "aiida.orm.StructureData",
   "aiida_cusp.utils.exceptions.KpointWrapperError",
   "pymatgen.core.Structure",
   "pymatgen.io.vasp.inputs.Poscar"
  ],
  "type": "function"
 },
 "aiida_cusp.data.inputs.vasp_kpoint.KpointWrapper.validate_and_initialize": {
  "lineno": 138,
  "symbols_in_volume": [
   "aiida_cusp.utils.exceptions.KpointWrapperError"
  ],
  "type": "function"
 },
 "aiida_cusp.data.inputs.vasp_kpoint.VaspKpointData": {
  "lineno": 19,
  "symbols_in_volume": [
   "aiida.orm.Dict"
  ],
  "type": "class"
 },
 "aiida_cusp.data.inputs.vasp_kpoint.VaspKpointData.__init__": {
  "lineno": 36,
  "symbols_in_volume": [],
  "type": "function"
 },
 "aiida_cusp.data.inputs.vasp_kpoint.VaspKpointData.get_description": {
  "lineno": 72,
  "symbols_in_volume": [],
  "type": "function"
 },
 "aiida_cusp.data.inputs.vasp_kpoint.VaspKpointData.get_kpoints": {
  "lineno": 46,
  "symbols_in_volume": [
   "pymatgen.io.vasp.inputs.Kpoints.from_dict"
  ],
  "type": "function"
 },
 "aiida_cusp.data.inputs.vasp_kpoint.VaspKpointData.write_file": {
  "lineno": 56,
  "symbols_in_volume": [],
  "type": "function"
 },
 "aiida_cusp.data.inputs.vasp_poscar": {
  "lineno": null,
  "symbols_in_volume": [],
  "type": "module"
 },
 "aiida_cusp.data.inputs.vasp_poscar.PoscarWrapper": {
  "lineno": 112,
  "symbols_in_volume": [],
  "type": "class"
 },
 "aiida_cusp.data.inputs.vasp_poscar.PoscarWrapper.__new__": {
  "lineno": 142,
  "symbols_in_volume": [
   "pymatgen.io.vasp.inputs.Poscar"
  ],
  "type": "function"
 },
 "aiida_cusp.data.inputs.vasp_poscar.PoscarWrapper.structure_from_input": {
  "lineno": 193,
  "symbols_in_volume": [
   "aiida.orm.StructureData",
   "aiida_cusp.utils.exceptions.PoscarWrapperError",
   "pymatgen.core.Structure"
  ],
  "type": "function"
 },
 "aiida_cusp.data.inputs.vasp_poscar.PoscarWrapper.validate_and_initialize": {
  "lineno": 154,
  "symbols_in_volume": [
   "aiida_cusp.utils.exceptions.PoscarWrapperError",
   "pymatgen.io.vasp.inputs.Poscar"
  ],
  "type": "function"
 },
 "aiida_cusp.data.inputs.vasp_poscar.VaspPoscarData": {
  "lineno": 25,
  "symbols_in_volume": [
   "aiida.orm.Dict"
  ],
  "type": "class"
 },
 "aiida_cusp.data.inputs.vasp_poscar.VaspPoscarData.__init__": {
  "lineno": 26,
  "symbols_in_volume": [],
  "type": "function"
 },
 "aiida_cusp.data.inputs.vasp_poscar.VaspPoscarData.get_aiida_structure": {
  "lineno": 73,
  "symbols_in_volume": [
   "aiida.orm.StructureData"
  ],
  "type": "function"
 },
 "aiida_cusp.data.inputs.vasp_poscar.VaspPoscarData.get_atoms": {
  "lineno": 62,
  "symbols_in_volume": [
   "pymatgen.io.ase.AseAtomsAdaptor.get_atoms"
  ],
  "type": "function"
 },
 "aiida_cusp.data.inputs.vasp_poscar.VaspPoscarData.get_description": {
  "lineno": 100,
  "symbols_in_volume": [
   "re.sub"
  ],
  "type": "function"
 },
 "aiida_cusp.data.inputs.vasp_poscar.VaspPoscarData.get_poscar": {
  "lineno": 41,
  "symbols_in_volume": [
   "pymatgen.io.vasp.inputs.Poscar.from_dict"
  ],
  "type": "function"
 },
 "aiida_cusp.data.inputs.vasp_poscar.VaspPoscarData.get_structure": {
  "lineno": 51,
  "symbols_in_volume": [],
  "type": "function"
 },
 "aiida_cusp.data.inputs.vasp_poscar.VaspPoscarData.write_file": {
  "lineno": 84,
  "symbols_in_volume": [],
  "type": "function"
 },
 "aiida_cusp.data.inputs.vasp_potcar": {
  "lineno": null,
  "symbols_in_volume": [],
  "type": "module"
 },
 "aiida_cusp.data.inputs.vasp_potcar.VaspPotcarData": {
  "lineno": 274,
  "symbols_in_volume": [
   "aiida.orm.Dict"
  ],
  "type": "class"
 },
 "aiida_cusp.data.inputs.vasp_potcar.VaspPotcarData.__init__": {
  "lineno": 283,
  "symbols_in_volume": [],
  "type": "function"
 },
 "aiida_cusp.data.inputs.vasp_potcar.VaspPotcarData.element": {
  "lineno": 521,
  "symbols_in_volume": [],
  "type": "function"
 },
 "aiida_cusp.data.inputs.vasp_potcar.VaspPotcarData.filenode_uuid": {
  "lineno": 516,
  "symbols_in_volume": [],
  "type": "function"
 },
 "aiida_cusp.data.inputs.vasp_potcar.VaspPotcarData.from_structure": {
  "lineno": 337,
  "symbols_in_volume": [
   "aiida.orm.StructureData",
   "aiida_cusp.data.inputs.vasp_poscar.VaspPoscarData",
   "aiida_cusp.utils.exceptions.VaspPotcarDataError",
   "pymatgen.core.Structure",
   "pymatgen.io.vasp.inputs.Poscar"
  ],
  "type": "function"
 },
 "aiida_cusp.data.inputs.vasp_potcar.VaspPotcarData.functional": {
  "lineno": 506,
  "symbols_in_volume": [],
  "type": "function"
 },
 "aiida_cusp.data.inputs.vasp_potcar.VaspPotcarData.hash": {
  "lineno": 526,
  "symbols_in_volume": [],
  "type": "function"
 },
 "aiida_cusp.data.inputs.vasp_potcar.VaspPotcarData.init_from_tags": {
  "lineno": 292,
  "symbols_in_volume": [
   "aiida_cusp.utils.exceptions.VaspPotcarDataError"
  ],
  "type": "function"
 },
 "aiida_cusp.data.inputs.vasp_potcar.VaspPotcarData.load_potential_file_node": {
  "lineno": 531,
  "symbols_in_volume": [
   "aiida.common.exceptions.NotExistent",
   "aiida.orm.load_node",
   "aiida_cusp.utils.exceptions.VaspPotcarDataError"
  ],
  "type": "function"
 },
 "aiida_cusp.data.inputs.vasp_potcar.VaspPotcarData.name": {
  "lineno": 501,
  "symbols_in_volume": [],
  "type": "function"
 },
 "aiida_cusp.data.inputs.vasp_potcar.VaspPotcarData.potcar_from_linklist": {
  "lineno": 463,
  "symbols_in_volume": [
   "aiida_cusp.utils.exceptions.VaspPotcarDataError",
   "pymatgen.io.vasp.inputs.Potcar",
   "pymatgen.io.vasp.inputs.PotcarSingle"
  ],
  "type": "function"
 },
 "aiida_cusp.data.inputs.vasp_potcar.VaspPotcarData.potcar_props_from_name_list": {
  "lineno": 435,
  "symbols_in_volume": [
   "aiida_cusp.utils.exceptions.VaspPotcarDataError",
   "pymatgen.core.periodic_table.Element",
   "re.match"
  ],
  "type": "function"
 },
 "aiida_cusp.data.inputs.vasp_potcar.VaspPotcarData.version": {
  "lineno": 511,
  "symbols_in_volume": [],
  "type": "function"
 },
 "aiida_cusp.data.inputs.vasp_potcar.VaspPotcarFile": {
  "lineno": 34,
  "symbols_in_volume": [
   "aiida.orm.SinglefileData"
  ],
  "type": "class"
 },
 "aiida_cusp.data.inputs.vasp_potcar.VaspPotcarFile.__init__": {
  "lineno": 60,
  "symbols_in_volume": [],
  "type": "function"
 },
 "aiida_cusp.data.inputs.vasp_potcar.VaspPotcarFile._validate": {
  "lineno": 223,
  "symbols_in_volume": [],
  "type": "function"
 },
 "aiida_cusp.data.inputs.vasp_potcar.VaspPotcarFile.add_potential": {
  "lineno": 96,
  "symbols_in_volume": [
   "aiida_cusp.utils.PotcarParser"
  ],
  "type": "function"
 },
 "aiida_cusp.data.inputs.vasp_potcar.VaspPotcarFile.element": {
  "lineno": 84,
  "symbols_in_volume": [],
  "type": "function"
 },
 "aiida_cusp.data.inputs.vasp_potcar.VaspPotcarFile.from_tags": {
  "lineno": 171,
  "symbols_in_volume": [
   "aiida.orm.QueryBuilder",
   "aiida_cusp.utils.exceptions.VaspPotcarFileError"
  ],
  "type": "function"
 },
 "aiida_cusp.data.inputs.vasp_potcar.VaspPotcarFile.functional": {
  "lineno": 92,
  "symbols_in_volume": [],
  "type": "function"
 },
 "aiida_cusp.data.inputs.vasp_potcar.VaspPotcarFile.hash": {
  "lineno": 80,
  "symbols_in_volume": [],
  "type": "function"
 },
 "aiida_cusp.data.inputs.vasp_potcar.VaspPotcarFile.is_unique": {
  "lineno": 124,
  "symbols_in_volume": [
   "aiida_cusp.utils.exceptions.MultiplePotcarError"
  ],
  "type": "function"
 },
 "aiida_cusp.data.inputs.vasp_potcar.VaspPotcarFile.name": {
  "lineno": 76,
  "symbols_in_volume": [],
  "type": "function"
 },
 "aiida_cusp.data.inputs.vasp_potcar.VaspPotcarFile.validate_element": {
  "lineno": 233,
  "symbols_in_volume": [
   "aiida_cusp.utils.exceptions.VaspPotcarFileError",
   "pymatgen.core.periodic_table.Element"
  ],
  "type": "function"
 },
 "aiida_cusp.data.inputs.vasp_potcar.VaspPotcarFile.validate_functional": {
  "lineno": 264,
  "symbols_in_volume": [
   "aiida_cusp.utils.defaults.VaspDefaults.FUNCTIONAL_MAP.values",
   "aiida_cusp.utils.exceptions.VaspPotcarFileError"
  ],
  "type": "function"
 },
 "aiida_cusp.data.inputs.vasp_potcar.VaspPotcarFile.validate_name": {
  "lineno": 240,
  "symbols_in_volume": [
   "aiida_cusp.utils.exceptions.VaspPotcarFileError",
   "pymatgen.core.periodic_table.Element",
   "re.match"
  ],
  "type": "function"
 },
 "aiida_cusp.data.inputs.vasp_potcar.VaspPotcarFile.validate_version": {
  "lineno": 253,
  "symbols_in_volume": [
   "aiida_cusp.utils.exceptions.VaspPotcarFileError"
  ],
  "type": "function"
 },
 "aiida_cusp.data.inputs.vasp_potcar.VaspPotcarFile.version": {
  "lineno": 88,
  "symbols_in_volume": [],
  "type": "function"
 },
 "aiida_cusp.data.outputs": {
  "lineno": null,
  "symbols_in_volume": [],
  "type": "module"
 },
 "aiida_cusp.data.outputs.vasp_chgcar": {
  "lineno": null,
  "symbols_in_volume": [],
  "type": "module"
 },
 "aiida_cusp.data.outputs.vasp_chgcar.VaspChgcarData": {
  "lineno": 13,
  "symbols_in_volume": [
   "aiida_cusp.utils.single_archive_data.SingleArchiveData"
  ],
  "type": "class"
 },
 "aiida_cusp.data.outputs.vasp_contcar": {
  "lineno": null,
  "symbols_in_volume": [],
  "type": "module"
 },
 "aiida_cusp.data.outputs.vasp_contcar.VaspContcarData": {
  "lineno": 13,
  "symbols_in_volume": [
   "aiida_cusp.data.inputs.vasp_poscar.VaspPoscarData"
  ],
  "type": "class"
 },
 "aiida_cusp.data.outputs.vasp_contcar.VaspContcarData.get_contcar": {
  "lineno": 21,
  "symbols_in_volume": [],
  "type": "function"
 },
 "aiida_cusp.data.outputs.vasp_generic": {
  "lineno": null,
  "symbols_in_volume": [],
  "type": "module"
 },
 "aiida_cusp.data.outputs.vasp_generic.VaspGenericData": {
  "lineno": 13,
  "symbols_in_volume": [
   "aiida_cusp.utils.single_archive_data.SingleArchiveData"
  ],
  "type": "class"
 },
 "aiida_cusp.data.outputs.vasp_outcar": {
  "lineno": null,
  "symbols_in_volume": [],
  "type": "module"
 },
 "aiida_cusp.data.outputs.vasp_outcar.VaspOutcarData": {
  "lineno": 20,
  "symbols_in_volume": [
   "aiida_cusp.utils.single_archive_data.SingleArchiveData"
  ],
  "type": "class"
 },
 "aiida_cusp.data.outputs.vasp_outcar.VaspOutcarData.get_outcar": {
  "lineno": 26,
  "symbols_in_volume": [
   "pymatgen.io.vasp.outputs.Outcar"
  ],
  "type": "function"
 },
 "aiida_cusp.data.outputs.vasp_vasprun": {
  "lineno": null,
  "symbols_in_volume": [],
  "type": "module"
 },
 "aiida_cusp.data.outputs.vasp_vasprun.VaspVasprunData": {
  "lineno": 22,
  "symbols_in_volume": [
   "aiida_cusp.utils.single_archive_data.SingleArchiveData"
  ],
  "type": "class"
 },
 "aiida_cusp.data.outputs.vasp_vasprun.VaspVasprunData.get_vasprun": {
  "lineno": 28,
  "symbols_in_volume": [
   "pymatgen.io.vasp.outputs.Vasprun"
  ],
  "type": "function"
 },
 "aiida_cusp.data.outputs.vasp_vasprun.VaspVasprunData.parser_settings": {
  "lineno": 81,
  "symbols_in_volume": [
   "aiida_cusp.utils.defaults.VasprunParsingDefaults.PARSER_ARGS"
  ],
  "type": "function"
 },
 "aiida_cusp.data.outputs.vasp_wavecar": {
  "lineno": null,
  "symbols_in_volume": [],
  "type": "module"
 },
 "aiida_cusp.data.outputs.vasp_wavecar.VaspWavecarData": {
  "lineno": 13,
  "symbols_in_volume": [
   "aiida_cusp.utils.single_archive_data.SingleArchiveData"
  ],
  "type": "class"
 },
 "aiida_cusp.parsers": {
  "lineno": null,
  "symbols_in_volume": [],
  "type": "module"
 },
 "aiida_cusp.parsers.parser_base": {
  "lineno": null,
  "symbols_in_volume": [],
  "type": "module"
 },
 "aiida_cusp.parsers.parser_base.ParserBase": {
  "lineno": 17,
  "symbols_in_volume": [
   "aiida.parsers.parser.Parser"
  ],
  "type": "class"
 },
 "aiida_cusp.parsers.parser_base.ParserBase.__init__": {
  "lineno": 24,
  "symbols_in_volume": [],
  "type": "function"
 },
 "aiida_cusp.parsers.parser_base.ParserBase.check_retrieved_temp_folder": {
  "lineno": 41,
  "symbols_in_volume": [],
  "type": "function"
 },
 "aiida_cusp.parsers.parser_base.ParserBase.complete_linkname": {
  "lineno": 63,
  "symbols_in_volume": [
   "aiida_cusp.utils.defaults.PluginDefaults.PARSER_OUTPUT_NAMESPACE"
  ],
  "type": "function"
 },
 "aiida_cusp.parsers.parser_base.ParserBase.parse": {
  "lineno": 34,
  "symbols_in_volume": [],
  "type": "function"
 },
 "aiida_cusp.parsers.parser_base.ParserBase.parser_settings": {
  "lineno": 54,
  "symbols_in_volume": [],
  "type": "function"
 },
 "aiida_cusp.parsers.parser_base.ParserBase.register_output_nodes": {
  "lineno": 72,
  "symbols_in_volume": [
   "aiida.common.exceptions.ModificationNotAllowed"
  ],
  "type": "function"
 },
 "aiida_cusp.parsers.vasp_file_parser": {
  "lineno": null,
  "symbols_in_volume": [],
  "type": "module"
 },
 "aiida_cusp.parsers.vasp_file_parser.VaspFileParser": {
  "lineno": 20,
  "symbols_in_volume": [
   "aiida_cusp.parsers.parser_base.ParserBase"
  ],
  "type": "class"
 },
 "aiida_cusp.parsers.vasp_file_parser.VaspFileParser.build_parsing_list": {
  "lineno": 97,
  "symbols_in_volume": [
   "aiida_cusp.utils.defaults.VaspDefaults.FNAMES",
   "pathlib.Path"
  ],
  "type": "function"
 },
 "aiida_cusp.parsers.vasp_file_parser.VaspFileParser.linkname": {
  "lineno": 84,
  "symbols_in_volume": [
   "aiida_cusp.utils.defaults.PluginDefaults.NEB_NODE_PREFIX",
   "re.match"
  ],
  "type": "function"
 },
 "aiida_cusp.parsers.vasp_file_parser.VaspFileParser.normalized_filename": {
  "lineno": 74,
  "symbols_in_volume": [],
  "type": "function"
 },
 "aiida_cusp.parsers.vasp_file_parser.VaspFileParser.parse": {
  "lineno": 48,
  "symbols_in_volume": [],
  "type": "function"
 },
 "aiida_cusp.parsers.vasp_file_parser.VaspFileParser.parse_chgcar": {
  "lineno": 160,
  "symbols_in_volume": [
   "aiida_cusp.data.VaspChgcarData"
  ],
  "type": "function"
 },
 "aiida_cusp.parsers.vasp_file_parser.VaspFileParser.parse_contcar": {
  "lineno": 150,
  "symbols_in_volume": [
   "aiida_cusp.data.VaspContcarData",
   "pymatgen.io.vasp.inputs.Poscar.from_file"
  ],
  "type": "function"
 },
 "aiida_cusp.parsers.vasp_file_parser.VaspFileParser.parse_generic": {
  "lineno": 176,
  "symbols_in_volume": [
   "aiida_cusp.data.VaspGenericData"
  ],
  "type": "function"
 },
 "aiida_cusp.parsers.vasp_file_parser.VaspFileParser.parse_outcar": {
  "lineno": 142,
  "symbols_in_volume": [
   "aiida_cusp.data.VaspOutcarData"
  ],
  "type": "function"
 },
 "aiida_cusp.parsers.vasp_file_parser.VaspFileParser.parse_vasprun_xml": {
  "lineno": 134,
  "symbols_in_volume": [
   "aiida_cusp.data.VaspVasprunData"
  ],
  "type": "function"
 },
 "aiida_cusp.parsers.vasp_file_parser.VaspFileParser.parse_wavecar": {
  "lineno": 168,
  "symbols_in_volume": [
   "aiida_cusp.data.VaspWavecarData"
  ],
  "type": "function"
 },
 "aiida_cusp.parsers.vasp_file_parser.VaspFileParser.parsing_hook": {
  "lineno": 81,
  "symbols_in_volume": [],
  "type": "function"
 },
 "aiida_cusp.parsers.vasp_file_parser.VaspFileParser.verify_and_set_parser_settings": {
  "lineno": 120,
  "symbols_in_volume": [],
  "type": "function"
 },
 "aiida_cusp.utils": {
  "lineno": null,
  "symbols_in_volume": [],
  "type": "module"
 },
 "aiida_cusp.utils.custodian": {
  "lineno": null,
  "symbols_in_volume": [],
  "type": "module"
 },
 "aiida_cusp.utils.custodian.CustodianSettings": {
  "lineno": 16,
  "symbols_in_volume": [],
  "type": "class"
 },
 "aiida_cusp.utils.custodian.CustodianSettings.__init__": {
  "lineno": 39,
  "symbols_in_volume": [],
  "type": "function"
 },
 "aiida_cusp.utils.custodian.CustodianSettings.setup_custodian_handlers": {
  "lineno": 86,
  "symbols_in_volume": [
   "aiida_cusp.utils.defaults.CustodianDefaults.ERROR_HANDLER_SETTINGS",
   "aiida_cusp.utils.defaults.CustodianDefaults.HANDLER_IMPORT_PATH",
   "aiida_cusp.utils.exceptions.CustodianSettingsError"
  ],
  "type": "function"
 },
 "aiida_cusp.utils.custodian.CustodianSettings.setup_custodian_settings": {
  "lineno": 54,
  "symbols_in_volume": [
   "aiida_cusp.utils.defaults.CustodianDefaults.CUSTODIAN_SETTINGS",
   "aiida_cusp.utils.defaults.CustodianDefaults.MODIFIABLE_SETTINGS",
   "aiida_cusp.utils.exceptions.CustodianSettingsError"
  ],
  "type": "function"
 },
 "aiida_cusp.utils.custodian.CustodianSettings.setup_vaspjob_settings": {
  "lineno": 145,
  "symbols_in_volume": [
   "aiida_cusp.utils.defaults.CustodianDefaults.VASP_JOB_SETTINGS",
   "aiida_cusp.utils.defaults.CustodianDefaults.VASP_NEB_JOB_SETTINGS"
  ],
  "type": "function"
 },
 "aiida_cusp.utils.custodian.CustodianSettings.validate_handlers": {
  "lineno": 175,
  "symbols_in_volume": [
   "aiida_cusp.utils.exceptions.CustodianSettingsError"
  ],
  "type": "function"
 },
 "aiida_cusp.utils.custodian.CustodianSettings.validate_settings": {
  "lineno": 190,
  "symbols_in_volume": [
   "aiida_cusp.utils.exceptions.CustodianSettingsError"
  ],
  "type": "function"
 },
 "aiida_cusp.utils.custodian.CustodianSettings.write_custodian_spec": {
  "lineno": 205,
  "symbols_in_volume": [
   "aiida_cusp.utils.defaults.CustodianDefaults.VASP_JOB_IMPORT_PATH",
   "aiida_cusp.utils.defaults.CustodianDefaults.VASP_NEB_JOB_IMPORT_PATH",
   "aiida_cusp.utils.exceptions.CustodianSettingsError",
   "yaml.dump"
  ],
  "type": "function"
 },
 "aiida_cusp.utils.decorators": {
  "lineno": null,
  "symbols_in_volume": [],
  "type": "module"
 },
 "aiida_cusp.utils.decorators.classproperty": {
  "lineno": 10,
  "symbols_in_volume": [],
  "type": "class"
 },
 "aiida_cusp.utils.decorators.classproperty.__get__": {
  "lineno": 15,
  "symbols_in_volume": [],
  "type": "function"
 },
 "aiida_cusp.utils.decorators.classproperty.__init__": {
  "lineno": 12,
  "symbols_in_volume": [],
  "type": "function"
 },
 "aiida_cusp.utils.defaults": {
  "lineno": null,
  "symbols_in_volume": [],
  "type": "module"
 },
 "aiida_cusp.utils.defaults.CustodianDefaults": {
  "lineno": 105,
  "symbols_in_volume": [],
  "type": "class"
 },
 "aiida_cusp.utils.defaults.CustodianDefaults.CUSTODIAN_SETTINGS": {
  "lineno": 166,
  "symbols_in_volume": [
   "aiida_cusp.utils.decorators.classproperty"
  ],
  "type": "function"
 },
 "aiida_cusp.utils.defaults.CustodianDefaults.ERROR_HANDLER_SETTINGS": {
  "lineno": 191,
  "symbols_in_volume": [
   "aiida_cusp.utils.decorators.classproperty"
  ],
  "type": "function"
 },
 "aiida_cusp.utils.defaults.CustodianDefaults.HANDLER_IMPORT_PATH": {
  "lineno": 116,
  "symbols_in_volume": [
   "aiida_cusp.utils.decorators.classproperty"
  ],
  "type": "function"
 },
 "aiida_cusp.utils.defaults.CustodianDefaults.MODIFIABLE_SETTINGS": {
  "lineno": 184,
  "symbols_in_volume": [
   "aiida_cusp.utils.decorators.classproperty"
  ],
  "type": "function"
 },
 "aiida_cusp.utils.defaults.CustodianDefaults.RUN_LOG_FNAME": {
  "lineno": 111,
  "symbols_in_volume": [
   "aiida_cusp.utils.decorators.classproperty"
  ],
  "type": "function"
 },
 "aiida_cusp.utils.defaults.CustodianDefaults.VASP_JOB_IMPORT_PATH": {
  "lineno": 125,
  "symbols_in_volume": [
   "aiida_cusp.utils.decorators.classproperty"
  ],
  "type": "function"
 },
 "aiida_cusp.utils.defaults.CustodianDefaults.VASP_JOB_SETTINGS": {
  "lineno": 130,
  "symbols_in_volume": [
   "aiida_cusp.utils.decorators.classproperty"
  ],
  "type": "function"
 },
 "aiida_cusp.utils.defaults.CustodianDefaults.VASP_NEB_JOB_IMPORT_PATH": {
  "lineno": 121,
  "symbols_in_volume": [
   "aiida_cusp.utils.decorators.classproperty"
  ],
  "type": "function"
 },
 "aiida_cusp.utils.defaults.CustodianDefaults.VASP_NEB_JOB_SETTINGS": {
  "lineno": 148,
  "symbols_in_volume": [
   "aiida_cusp.utils.decorators.classproperty"
  ],
  "type": "function"
 },
 "aiida_cusp.utils.defaults.PluginDefaults": {
  "lineno": 71,
  "symbols_in_volume": [],
  "type": "class"
 },
 "aiida_cusp.utils.defaults.PluginDefaults.CSTDN_SPEC_FNAME": {
  "lineno": 82,
  "symbols_in_volume": [
   "aiida_cusp.utils.decorators.classproperty"
  ],
  "type": "function"
 },
 "aiida_cusp.utils.defaults.PluginDefaults.NEB_NODE_PREFIX": {
  "lineno": 87,
  "symbols_in_volume": [
   "aiida_cusp.utils.decorators.classproperty"
  ],
  "type": "function"
 },
 "aiida_cusp.utils.defaults.PluginDefaults.NEB_NODE_REGEX": {
  "lineno": 92,
  "symbols_in_volume": [
   "aiida_cusp.utils.decorators.classproperty",
   "re.compile"
  ],
  "type": "function"
 },
 "aiida_cusp.utils.defaults.PluginDefaults.PARSER_OUTPUT_NAMESPACE": {
  "lineno": 100,
  "symbols_in_volume": [
   "aiida_cusp.utils.decorators.classproperty"
  ],
  "type": "function"
 },
 "aiida_cusp.utils.defaults.PluginDefaults.STDERR_FNAME": {
  "lineno": 73,
  "symbols_in_volume": [
   "aiida_cusp.utils.decorators.classproperty"
  ],
  "type": "function"
 },
 "aiida_cusp.utils.defaults.PluginDefaults.STDOUT_FNAME": {
  "lineno": 77,
  "symbols_in_volume": [
   "aiida_cusp.utils.decorators.classproperty"
  ],
  "type": "function"
 },
 "aiida_cusp.utils.defaults.VaspDefaults": {
  "lineno": 12,
  "symbols_in_volume": [],
  "type": "class"
 },
 "aiida_cusp.utils.defaults.VaspDefaults.FNAMES": {
  "lineno": 34,
  "symbols_in_volume": [
   "aiida_cusp.utils.decorators.classproperty"
  ],
  "type": "function"
 },
 "aiida_cusp.utils.defaults.VaspDefaults.FUNCTIONAL_MAP": {
  "lineno": 17,
  "symbols_in_volume": [
   "aiida_cusp.utils.decorators.classproperty"
  ],
  "type": "function"
 },
 "aiida_cusp.utils.defaults.VasprunParsingDefaults": {
  "lineno": 244,
  "symbols_in_volume": [],
  "type": "class"
 },
 "aiida_cusp.utils.defaults.VasprunParsingDefaults.PARSER_ARGS": {
  "lineno": 250,
  "symbols_in_volume": [
   "aiida_cusp.utils.decorators.classproperty"
  ],
  "type": "function"
 },
 "aiida_cusp.utils.exceptions": {
  "lineno": null,
  "symbols_in_volume": [],
  "type": "module"
 },
 "aiida_cusp.utils.exceptions.CommandLineError": {
  "lineno": 49,
  "symbols_in_volume": [],
  "type": "class"
 },
 "aiida_cusp.utils.exceptions.CustodianSettingsError": {
  "lineno": 54,
  "symbols_in_volume": [],
  "type": "class"
 },
 "aiida_cusp.utils.exceptions.IncarWrapperError": {
  "lineno": 19,
  "symbols_in_volume": [],
  "type": "class"
 },
 "aiida_cusp.utils.exceptions.KpointWrapperError": {
  "lineno": 24,
  "symbols_in_volume": [],
  "type": "class"
 },
 "aiida_cusp.utils.exceptions.MultiplePotcarError": {
  "lineno": 44,
  "symbols_in_volume": [],
  "type": "class"
 },
 "aiida_cusp.utils.exceptions.PoscarWrapperError": {
  "lineno": 29,
  "symbols_in_volume": [],
  "type": "class"
 },
 "aiida_cusp.utils.exceptions.PotcarParserError": {
  "lineno": 9,
  "symbols_in_volume": [],
  "type": "class"
 },
 "aiida_cusp.utils.exceptions.PotcarPathError": {
  "lineno": 14,
  "symbols_in_volume": [],
  "type": "class"
 },
 "aiida_cusp.utils.exceptions.VaspPotcarDataError": {
  "lineno": 39,
  "symbols_in_volume": [],
  "type": "class"
 },
 "aiida_cusp.utils.exceptions.VaspPotcarFileError": {
  "lineno": 34,
  "symbols_in_volume": [],
  "type": "class"
 },
 "aiida_cusp.utils.potcar": {
  "lineno": null,
  "symbols_in_volume": [],
  "type": "module"
 },
 "aiida_cusp.utils.potcar.PotcarParser": {
  "lineno": 18,
  "symbols_in_volume": [
   "re.compile"
  ],
  "type": "class"
 },
 "aiida_cusp.utils.potcar.PotcarParser.__init__": {
  "lineno": 121,
  "symbols_in_volume": [],
  "type": "function"
 },
 "aiida_cusp.utils.potcar.PotcarParser.apply_quirks": {
  "lineno": 137,
  "symbols_in_volume": [],
  "type": "function"
 },
 "aiida_cusp.utils.potcar.PotcarParser.hash_contents": {
  "lineno": 188,
  "symbols_in_volume": [
   "hashlib.sha256"
  ],
  "type": "function"
 },
 "aiida_cusp.utils.potcar.PotcarParser.load_potential_contents": {
  "lineno": 177,
  "symbols_in_volume": [],
  "type": "function"
 },
 "aiida_cusp.utils.potcar.PotcarParser.load_reduced_contents": {
  "lineno": 162,
  "symbols_in_volume": [],
  "type": "function"
 },
 "aiida_cusp.utils.potcar.PotcarParser.potential_element": {
  "lineno": 227,
  "symbols_in_volume": [],
  "type": "function"
 },
 "aiida_cusp.utils.potcar.PotcarParser.potential_header": {
  "lineno": 213,
  "symbols_in_volume": [],
  "type": "function"
 },
 "aiida_cusp.utils.potcar.PotcarParser.potential_title": {
  "lineno": 201,
  "symbols_in_volume": [
   "aiida_cusp.utils.exceptions.PotcarParserError"
  ],
  "type": "function"
 },
 "aiida_cusp.utils.potcar.PotcarParser.potential_version": {
  "lineno": 241,
  "symbols_in_volume": [
   "re.findall",
   "re.search",
   "warnings.warn"
  ],
  "type": "function"
 },
 "aiida_cusp.utils.potcar.PotcarParser.verify_parsed": {
  "lineno": 148,
  "symbols_in_volume": [
   "aiida_cusp.utils.exceptions.PotcarParserError"
  ],
  "type": "function"
 },
 "aiida_cusp.utils.potcar.PotcarPathParser": {
  "lineno": 291,
  "symbols_in_volume": [],
  "type": "class"
 },
 "aiida_cusp.utils.potcar.PotcarPathParser.__init__": {
  "lineno": 308,
  "symbols_in_volume": [],
  "type": "function"
 },
 "aiida_cusp.utils.potcar.PotcarPathParser.parse_functional": {
  "lineno": 330,
  "symbols_in_volume": [
   "aiida_cusp.utils.defaults.VaspDefaults.FUNCTIONAL_MAP",
   "aiida_cusp.utils.exceptions.PotcarPathError",
   "re.search"
  ],
  "type": "function"
 },
 "aiida_cusp.utils.potcar.PotcarPathParser.parse_name": {
  "lineno": 358,
  "symbols_in_volume": [],
  "type": "function"
 },
 "aiida_cusp.utils.potcar.PotcarPathParser.validate_path_is_potcar_file": {
  "lineno": 315,
  "symbols_in_volume": [
   "aiida_cusp.utils.defaults.VaspDefaults.FNAMES",
   "aiida_cusp.utils.exceptions.PotcarPathError"
  ],
  "type": "function"
 },
 "aiida_cusp.utils.single_archive_data": {
  "lineno": null,
  "symbols_in_volume": [],
  "type": "module"
 },
 "aiida_cusp.utils.single_archive_data.SingleArchiveData": {
  "lineno": 17,
  "symbols_in_volume": [
   "aiida.orm.SinglefileData"
  ],
  "type": "class"
 },
 "aiida_cusp.utils.single_archive_data.SingleArchiveData.filepath": {
  "lineno": 105,
  "symbols_in_volume": [],
  "type": "function"
 },
 "aiida_cusp.utils.single_archive_data.SingleArchiveData.get_compressed_file_contents": {
  "lineno": 50,
  "symbols_in_volume": [
   "gzip.compress",
   "io.BytesIO",
   "pathlib.Path"
  ],
  "type": "function"
 },
 "aiida_cusp.utils.single_archive_data.SingleArchiveData.get_content": {
  "lineno": 69,
  "symbols_in_volume": [
   "gzip.decompress"
  ],
  "type": "function"
 },
 "aiida_cusp.utils.single_archive_data.SingleArchiveData.set_file": {
  "lineno": 27,
  "symbols_in_volume": [],
  "type": "function"
 },
 "aiida_cusp.utils.single_archive_data.SingleArchiveData.write_file": {
  "lineno": 85,
  "symbols_in_volume": [
   "pathlib.Path"
  ],
  "type": "function"
 }
}